libm_ext-0.0.2.dist-info/METADATA
libm_ext-0.0.2.dist-info/WHEEL
libm_ext-0.0.2.dist-info/licenses/LICENSE-APACHE
libm_ext-0.0.2.dist-info/licenses/LICENSE-MIT
libm_ext/__init__.py
libm_ext/_core.abi3.so
libm_ext/_core.pyi
libm_ext/py.typed
libm_ext/trig.py
libm_ext/vectorized/__init__.py
libm_ext/vectorized/trig.py
libm_ext/vectorized/utils.py
libm_ext-0.0.2.dist-info/RECORD
