Metadata-Version: 2.4
Name: libm-ext
Version: 0.0.2
Classifier: Development Status :: 4 - Beta
Classifier: Intended Audience :: Science/Research
Classifier: License :: OSI Approved :: MIT License
Classifier: Operating System :: OS Independent
Classifier: Programming Language :: Python :: 3
Classifier: Programming Language :: Python :: 3.11
Classifier: Programming Language :: Python :: 3.12
Classifier: Programming Language :: Python :: 3.13
Classifier: Programming Language :: Python :: 3.14
Classifier: Programming Language :: Rust
Classifier: Topic :: Scientific/Engineering :: Mathematics
Classifier: Typing :: Typed
Requires-Dist: numpy>=2.3.5
License-File: LICENSE-APACHE
License-File: LICENSE-MIT
Summary: A Python package wrapping the essential mathematical special functions in libm-ext with vectorized support.
Author-email: tangxiangong <tangxiangong@gmail.com>
License-Expression: MIT OR Apache-2.0
Requires-Python: >=3.11
